<?xml version='1.0' encoding='utf-8'?>
<GLEIFResults><Timestamp>2025-09-15T23:48:01.362770</Timestamp><Matches><Match><LegalName>THE TRAVIS RYLE PRIVATE BANK SAMPLE ENTITY</LegalName><Country>US</Country><LEI>254900SAMPLE1234567890</LEI></Match><Match><LegalName>THE TRAVIS RYLE PRIVATE BANK SAMPLE ENTITY</LegalName><Country>US</Country><LEI>254900SAMPLE1234567890</LEI></Match><Match><LegalName>THE TRAVIS RYLE PRIVATE BANK SAMPLE ENTITY</LegalName><Country>US</Country><LEI>254900SAMPLE1234567890</LEI></Match><Match><LegalName>RYLE PRIVATE BANK SAMPLE MATCH</LegalName><Country>US</Country><LEI>254900SAMPLE1234567892</LEI></Match></Matches></GLEIFResults>